{"ast":null,"code":"import { BNav } from './nav';\nimport { BNavItem } from './nav-item';\nimport { BNavText } from './nav-text';\nimport { BNavForm } from './nav-form';\nimport { BNavItemDropdown } from './nav-item-dropdown';\nimport { DropdownPlugin } from '../dropdown';\nimport { pluginFactory } from '../../utils/plugins';\nvar NavPlugin =\n/*#__PURE__*/\npluginFactory({\n  components: {\n    BNav: BNav,\n    BNavItem: BNavItem,\n    BNavText: BNavText,\n    BNavForm: BNavForm,\n    BNavItemDropdown: BNavItemDropdown,\n    BNavItemDd: BNavItemDropdown,\n    BNavDropdown: BNavItemDropdown,\n    BNavDd: BNavItemDropdown\n  },\n  plugins: {\n    DropdownPlugin: DropdownPlugin\n  }\n});\nexport { NavPlugin, BNav, BNavItem, BNavText, BNavForm, BNavItemDropdown };","map":null,"metadata":{},"sourceType":"module"}